geocleaner/__init__.py
geocleaner/core.py
geocleaner/tests/test_core.py
geocleaner-0.1.3.dist-info/METADATA
geocleaner-0.1.3.dist-info/WHEEL
geocleaner-0.1.3.dist-info/top_level.txt
geocleaner-0.1.3.dist-info/RECORD
