Metadata-Version: 2.4
Name: geocleaner
Version: 0.1.3
Summary: A simple package for cleaning geolocation strings.
Author-email: Nelofar Qulizada <nqulizada835@gmail.com>
License:                                  Apache License
Project-URL: Homepage, https://github.com/nqulizada835/geocleaner
Requires-Python: >=3.7
Provides-Extra: docs
Requires-Dist: sphinx; extra == "docs"
Requires-Dist: sphinx_rtd_theme; extra == "docs"
